ublcii/__about__.py
ublcii/__init__.py
ublcii/translate.py
ublcii/bots/botssys/sqlitedb/botsdb
ublcii/bots/config/__init__.py
ublcii/bots/config/bots.ini
ublcii/bots/config/settings.py
ublcii/bots/usersys/__init__.py
ublcii/bots/usersys/index.py
ublcii/bots/usersys/communicationscripts/__init__.py
ublcii/bots/usersys/communicationscripts/bots_file_in.py
ublcii/bots/usersys/communicationscripts/bots_file_out.py
ublcii/bots/usersys/grammars/__init__.py
ublcii/bots/usersys/grammars/xml/D16B_CII.py
ublcii/bots/usersys/grammars/xml/D16Brecords.py
ublcii/bots/usersys/grammars/xml/D16Bsequences.py
ublcii/bots/usersys/grammars/xml/UBL21_CreditNote.py
ublcii/bots/usersys/grammars/xml/UBL21_INVOICE.py
ublcii/bots/usersys/grammars/xml/UBL21records.py
ublcii/bots/usersys/grammars/xml/UBL21sequences.py
ublcii/bots/usersys/grammars/xml/__init__.py
ublcii/bots/usersys/mappings/__init__.py
ublcii/bots/usersys/mappings/xml/D16B_cii2xmlUBL21_invoice.py
ublcii/bots/usersys/mappings/xml/UBL21_invoice2xmlD16B_cii.py
ublcii/bots/usersys/mappings/xml/__init__.py
ublcii/bots/usersys/routescripts/CII_2_UBL.py
ublcii/bots/usersys/routescripts/UBL_2_CII.py
ublcii/bots/usersys/routescripts/__init__.py
ublcii/java/Saxon-HE.jar
ublcii2-1.1.8.dist-info/licenses/LICENSE
ublcii2-1.1.8.dist-info/METADATA
ublcii2-1.1.8.dist-info/WHEEL
ublcii2-1.1.8.dist-info/entry_points.txt
ublcii2-1.1.8.dist-info/top_level.txt
ublcii2-1.1.8.dist-info/RECORD
